[
    {
        "count_commentss": 38,
        "count_reactions": 0,
        "count_shares": 1,
        "created_time": "2018-05-30 18:00:01",
        "id": "376570488117_10156474615373118",
        "link": "http://news.chosun.com/site/data/html_dir/2018/05/30/2018053002347.html?Dep0=facebook&news",
        "message": "K-9 폭발사고 당한 이찬호 병장, 국가유공자 된다",
        "name": "K-9 폭발사고 당한 이찬호 병장, 국가유공자 된다",
        "type": "link"
    },
    {
        "count_commentss": 15,
        "count_reactions": 0,
        "count_shares": 1,
        "created_time": "2018-05-30 17:44:43",
        "id": "376570488117_10156474665613118",
        "link": "http://news.chosun.com/site/data/html_dir/2018/05/30/2018053002620.html?Dep0=facebook&news",
        "message": "김정은, 눈물 흘리는 영상까지 제작했다는데…",
        "name": "김정은 ‘경제발전 의지’ 어느 정도일까…눈물 흘리는 영상까지 제작",
        "type": "link"
    },
    {
        "count_commentss": 4,
        "count_reactions": 0,
        "count_shares": 1,
        "created_time": "2018-05-30 17:30:00",
        "id": "376570488117_10156474632488118",
        "link": "http://news.chosun.com/site/data/html_dir/2018/05/23/2018052302864.html?Dep0=facebook&news",
        "message": "'글로벌 TOP 5'로 성장한 현대기아차가 중국과 미국서 고전하는 이유는…",
        "name": "[비상등 켠 현대차]② 美·中빅마켓서 고전… 판매량 회복까지 최소 5년",
        "type": "link"
    },
    {
        "count_commentss": 10,
        "count_reactions": 0,
        "count_shares": 4,
        "created_time": "2018-05-30 17:17:37",
        "id": "376570488117_10156474636753118",
        "link": "http://news.chosun.com/site/data/html_dir/2018/05/30/2018053002605.html?Dep0=facebook&news",
        "message": "[단독]1600만원 일본 '후뢰시맨' 의상 '무관세'로 들어왔다",
        "name": "[단독]1600만원 일본 '후뢰시맨' 의상 '무관세'로 들어왔다",
        "type": "link"
    },
    {
        "count_commentss": 1,
        "count_reactions": 0,
        "count_shares": 0,
        "created_time": "2018-05-30 17:00:01",
        "id": "376570488117_10156474151798118",
        "link": "http://news.chosun.com/site/data/html_dir/2018/05/30/2018053000236.html?Dep0=facebook&news",
        "message": "러시아 국보급 名畵 찢은 취객에 내려진 형벌은…",
        "name": "러시아의 세계적 名畵 '이반 뇌제와 아들', 보드카 취객이 찢었다",
        "type": "link"
    },
    {
        "count_commentss": 7,
        "count_reactions": 0,
        "count_shares": 0,
        "created_time": "2018-05-30 17:00:01",
        "id": "376570488117_10156474582008118",
        "link": "http://news.chosun.com/site/data/html_dir/2018/05/30/2018053002283.html?Dep0=facebook&news",
        "message": "조명균 \"북미 간 비핵화 입장차 여전…조율 불가능하진 않다\"",
        "name": "조명균 \"북미 간 비핵화 입장차 여전…조율 불가능하진 않아\"",
        "type": "link"
    },
    {
        "count_commentss": 11,
        "count_reactions": 0,
        "count_shares": 6,
        "created_time": "2018-05-30 16:30:00",
        "id": "376570488117_10156474455458118",
        "link": "http://news.chosun.com/site/data/html_dir/2018/05/30/2018053001699.html?Dep0=facebook&news",
        "message": "이낙연 \"(비핵화는 미국이 주도한다는) 기조는 한미 공동선언에 이미 다 합의돼 있다\"",
        "name": "\"北비핵화는 미국이 당사자\"라는 이낙연",
        "type": "link"
    },
    {
        "count_commentss": 12,
        "count_reactions": 0,
        "count_shares": 8,
        "created_time": "2018-05-30 16:00:01",
        "id": "376570488117_10156474428448118",
        "link": "http://news.chosun.com/site/data/html_dir/2018/05/30/2018053001590.html?Dep0=facebook&news",
        "message": "“배우자 구합니다.” \n\n생활정보지 광고로 만나 성사된 ‘황혼 재혼’ 한 달 만에 남편은 33차례나 칼에 찔렸다.",
        "name": "[수사반장]살인극으로 끝난 '교차로 재혼', 남편 33차례 찔러 살해",
        "type": "link"
    },
    {
        "count_commentss": 18,
        "count_reactions": 0,
        "count_shares": 1,
        "created_time": "2018-05-30 15:45:00",
        "id": "376570488117_10156474449308118",
        "link": "http://news.chosun.com/site/data/html_dir/2018/05/30/2018053001843.html?Dep0=facebook&news",
        "message": "탈북 女종업원 송환 문제 고위급회담서 다뤄지나",
        "name": "탈북 女종업원 송환 문제 고위급회담서 다뤄지나…통일부 \"대화로 문제 해결\"",
        "type": "link"
    },
    {
        "count_commentss": 5,
        "count_reactions": 0,
        "count_shares": 0,
        "created_time": "2018-05-30 15:21:11",
        "id": "376570488117_10156474485248118",
        "link": "http://biz.chosun.com/site/data/html_dir/2018/05/30/2018053001687.html?Dep0=facebook&news",
        "message": "삼성생명이 삼성전자 보유 지분 1조원을 블록딜(시간외 대량매매)로 매각한다",
        "name": "[단독] 삼성생명, 삼성전자 지분 1조원 블록딜 매각",
        "type": "link"
    },
    {
        "count_commentss": 14,
        "count_reactions": 0,
        "count_shares": 0,
        "created_time": "2018-05-30 15:00:00",
        "id": "376570488117_10156474425538118",
        "link": "http://news.chosun.com/site/data/html_dir/2018/05/30/2018053001584.html?Dep0=facebook&news",
        "message": "다음 ‘아이스버킷 챌린지’ 참여자로 배우 곽동연, 여진구, 이준혁을 지목했다",
        "name": "션 이어 박보검도 아이스버킷 동참…\"루게릭 요양병원 응원\"",
        "type": "link"
    },
    {
        "count_commentss": 5,
        "count_reactions": 0,
        "count_shares": 3,
        "created_time": "2018-05-30 14:30:00",
        "id": "376570488117_10156474400868118",
        "link": "http://biz.chosun.com/site/data/html_dir/2018/05/30/2018053001324.html?Dep0=facebook&news",
        "message": "소득 하위와 상위 20% 가구의 교육비 지출 격차는 10배에 달했다",
        "name": "전체 가구중 18.2% '적자'…소득 상하위 교육비 격차 10배",
        "type": "link"
    },
    {
        "count_commentss": 16,
        "count_reactions": 0,
        "count_shares": 3,
        "created_time": "2018-05-30 14:15:00",
        "id": "376570488117_10156474390888118",
        "link": "http://news.chosun.com/site/data/html_dir/2018/05/30/2018053000956.html?Dep0=facebook&news",
        "message": "경기지사 토론회서 언급된 '이재명, 여배우 스캔들'",
        "name": "경기지사 토론회서 언급된 '이재명, 여배우 스캔들'",
        "type": "link"
    },
    {
        "count_commentss": 1,
        "count_reactions": 0,
        "count_shares": 0,
        "created_time": "2018-05-30 14:00:00",
        "id": "376570488117_10156474259853118",
        "link": "http://news.chosun.com/site/data/html_dir/2018/05/30/2018053001240.html?Dep0=facebook&news",
        "message": "의료과실로 ‘식물인간’ 됐는데... 배상책임은 30%?",
        "name": "[법과 마음 사이] 의료과실로 ‘식물인간’ 됐는데... 배상책임은 30%?",
        "type": "link"
    },
    {
        "count_commentss": 0,
        "count_reactions": 0,
        "count_shares": 0,
        "created_time": "2018-05-30 13:30:00",
        "id": "376570488117_10156474210728118",
        "link": "http://news.chosun.com/site/data/html_dir/2018/05/30/2018053001105.html?Dep0=facebook&news",
        "message": "서울시 \"119구급대원 폭행하면 손배소\"",
        "name": "서울시 \"119구급대 폭행하면 손해배상 소송\"…사전 합의도 원천 차단",
        "type": "link"
    },
    {
        "count_commentss": 8,
        "count_reactions": 0,
        "count_shares": 11,
        "created_time": "2018-05-30 13:00:01",
        "id": "376570488117_10156474154248118",
        "link": "http://biz.chosun.com/site/data/html_dir/2018/05/30/2018053000123.html?Dep0=facebook&news",
        "message": "정부자금 들인 혁신기술인데…개발 끝내니 \"의료법상 불법\"",
        "name": "한국은 혁신기술 개발해도… \"의료법상 불법입니다\"",
        "type": "link"
    },
    {
        "count_commentss": 4,
        "count_reactions": 0,
        "count_shares": 2,
        "created_time": "2018-05-30 12:30:00",
        "id": "376570488117_10156474189128118",
        "link": "http://news.chosun.com/site/data/html_dir/2018/05/30/2018053000803.html?Dep0=facebook&news",
        "message": "개각行 하마평 오르는 여당 의원은 누구?",
        "name": "총리발 개각설에 흔들리는 여당",
        "type": "link"
    },
    {
        "count_commentss": 14,
        "count_reactions": 0,
        "count_shares": 7,
        "created_time": "2018-05-30 12:00:01",
        "id": "376570488117_10156474149548118",
        "link": "http://biz.chosun.com/site/data/html_dir/2018/05/30/2018053000748.html?Dep0=facebook&news",
        "message": "[단독] 현대차, 함안 ‘쏘나타 의인’도 신차 준다",
        "name": "[단독] 현대차, 함안 ‘쏘나타 의인’도 신차 준다…'의인 포상 매뉴얼' 만들기로",
        "type": "link"
    },
    {
        "count_commentss": 3,
        "count_reactions": 0,
        "count_shares": 3,
        "created_time": "2018-05-30 11:45:00",
        "id": "376570488117_10156474148583118",
        "link": "http://news.chosun.com/site/data/html_dir/2018/05/30/2018053000391.html?Dep0=facebook&news",
        "message": "또 등장한 ''고속도로 고의사고 의인'",
        "name": "이번엔 함안에서 '착한 교통사고'",
        "type": "link"
    },
    {
        "count_commentss": 12,
        "count_reactions": 0,
        "count_shares": 5,
        "created_time": "2018-05-30 11:32:00",
        "id": "376570488117_10156474145118118",
        "link": "http://news.chosun.com/site/data/html_dir/2018/05/30/2018053000255.html?Dep0=facebook&news",
        "message": "정부가 기업 앞길 열어준 중국… 미래산업 전생서 한국이 안 보인다",
        "name": "중국, AI 의사와 스마트폰 상담… 원격진료 환자만 1억명",
        "type": "link"
    },
    {
        "count_commentss": 16,
        "count_reactions": 0,
        "count_shares": 18,
        "created_time": "2018-05-30 11:00:01",
        "id": "376570488117_10156474138423118",
        "link": "http://news.chosun.com/site/data/html_dir/2018/05/30/2018053000622.html?Dep0=kakao&news",
        "message": "美 CIA 보고서에 “북한은 앞으로 15년간 핵을 포기하지 않을 것”이라는 내용이 담겼다",
        "name": "美 CIA \"北, 핵 포기 가능성 없다…맥도날드 평양점은 열 수도\"",
        "type": "link"
    },
    {
        "count_commentss": 0,
        "count_reactions": 0,
        "count_shares": 0,
        "created_time": "2018-05-30 10:50:38",
        "id": "376570488117_10156474173738118",
        "link": "https://www.facebook.com/chosun/photos/a.10150175486148118.325596.376570488117/10156474161433118/?type=3",
        "message": "멜로망스 같은 뮤지션 또 없나\n#헬로루키 #튠업 #밴드디스커버리",
        "name": "Photos from 조선일보's post",
        "type": "photo"
    },
    {
        "count_commentss": 2,
        "count_reactions": 0,
        "count_shares": 2,
        "created_time": "2018-05-30 10:45:00",
        "id": "376570488117_10156474128098118",
        "link": "http://news.chosun.com/site/data/html_dir/2018/05/30/2018053000040.html?Dep0=facebook&news",
        "message": "천안서만 활동하고, 수감기간 짧다며 심사 당시 가장 낮은 등급을 받았다",
        "name": "'3·1운동 상징' 유관순 열사가 3등급 훈장?",
        "type": "link"
    },
    {
        "count_commentss": 6,
        "count_reactions": 0,
        "count_shares": 2,
        "created_time": "2018-05-30 10:43:27",
        "id": "376570488117_10156474167413118",
        "link": "http://news.chosun.com/site/data/html_dir/2018/05/30/2018053000941.html?Dep0=facebook&news",
        "message": "[속보] 정유라 학점 특혜 류철균 교수, 징역 1년·집유 2년",
        "name": "[속보] '정유라 학점 특혜' 류철균 교수, 징역 1년·집유 2년 확정",
        "type": "link"
    },
    {
        "count_commentss": 3,
        "count_reactions": 0,
        "count_shares": 6,
        "created_time": "2018-05-30 10:23:14",
        "id": "376570488117_10156474146138118",
        "link": "http://news.chosun.com/site/data/html_dir/2018/05/30/2018053000620.html?Dep0=facebook&news",
        "message": "미국 정부가 29일(현지 시각) 북한의 해킹 조직 ‘히든 코브라’에 대한 세 번째 경보를 발령했다",
        "name": "美 정부, 北 해킹조직 ‘히든 코브라’ 경보…“북한 정부가 배후”",
        "type": "link"
    },
    {
        "count_commentss": 3,
        "count_reactions": 0,
        "count_shares": 2,
        "created_time": "2018-05-30 10:03:34",
        "id": "376570488117_10156474121818118",
        "link": "http://news.chosun.com/site/data/html_dir/2018/05/30/2018053000050.html?Dep0=facebook&news",
        "message": "초등학생 머릿니, 학구열 높은 서울 강남과 목동 등에서 더 많이 발견된다는데…",
        "name": "[NOW] 초등학생 머릿니 급증, 학구열 높은 동네가 더 심하다는데…",
        "type": "link"
    },
    {
        "count_commentss": 14,
        "count_reactions": 0,
        "count_shares": 5,
        "created_time": "2018-05-30 09:38:29",
        "id": "376570488117_10156474093893118",
        "link": "http://biz.chosun.com/site/data/html_dir/2018/05/29/2018052902458.html?Dep0=facebook&news",
        "message": "文대통령 측근이 공영홈쇼핑 대표 후보에 포함됐다",
        "name": "[단독] 공영홈쇼핑 새 대표 후보에 문 대통령 측근 포함...선임되면 '낙하산 논란' 일듯",
        "type": "link"
    },
    {
        "count_commentss": 19,
        "count_reactions": 0,
        "count_shares": 14,
        "created_time": "2018-05-30 09:16:00",
        "id": "376570488117_10156474069713118",
        "link": "http://biz.chosun.com/site/data/html_dir/2018/05/29/2018052903690.html?Dep0=facebook&news",
        "message": "주 52시간 시행 한달 앞두고 삼성·LG전자 '알아서 출퇴근'",
        "name": "지금은 오후 2시… 부장님, 저 퇴근하겠습니다",
        "type": "link"
    },
    {
        "count_commentss": 3,
        "count_reactions": 0,
        "count_shares": 4,
        "created_time": "2018-05-29 23:30:01",
        "id": "376570488117_10156472890633118",
        "link": "http://news.chosun.com/site/data/html_dir/2018/05/29/2018052903224.html",
        "message": "“북한과의 정상회담을 위해 훌륭한 팀을 구성했다”",
        "name": "트럼프 \"北김영철, 지금 뉴욕으로 오고 있다\"",
        "type": "link"
    },
    {
        "count_commentss": 6,
        "count_reactions": 0,
        "count_shares": 0,
        "created_time": "2018-05-29 22:30:01",
        "id": "376570488117_10156472888123118",
        "link": "http://news.chosun.com/site/data/html_dir/2018/05/29/2018052903226.html",
        "message": "\"증여세 부과 처분을 취소하라\"",
        "name": "신격호 \"증여세 2126억원 부당하다\" 과세 불복 소송",
        "type": "link"
    },
    {
        "count_commentss": 35,
        "count_reactions": 0,
        "count_shares": 2,
        "created_time": "2018-05-29 21:25:34",
        "id": "376570488117_10156472881203118",
        "link": "http://news.chosun.com/site/data/html_dir/2018/05/29/2018052902934.html",
        "message": "“경제 살리려면 대통령 최측근이 돼야”…김경수, '힘 있는 도지사' 강조\n\n“여론조사? 밑바닥 민심은 모른다”…김태호, ‘능력 있는 도지사’ 홍보",
        "name": "[격전지 르포③경남] \"당 보고 찍는 시대 끝나…경제 살릴 사람 뽑는다\"",
        "type": "link"
    },
    {
        "count_commentss": 8,
        "count_reactions": 0,
        "count_shares": 0,
        "created_time": "2018-05-29 19:00:01",
        "id": "376570488117_10156472611703118",
        "link": "http://biz.chosun.com/site/data/html_dir/2018/05/29/2018052902043.html?Dep0=facebook&news",
        "message": "초청하지 않은 정확한 이유는 파악할 수 없어",
        "name": "대통령 가계소득 회의에 초청받지 못한 금융위원장...금융 홀대 논란",
        "type": "link"
    },
    {
        "count_commentss": 27,
        "count_reactions": 0,
        "count_shares": 2,
        "created_time": "2018-05-29 18:40:00",
        "id": "376570488117_10156472608878118",
        "link": "http://news.chosun.com/site/data/html_dir/2018/05/29/2018052902519.html?Dep0=facebook&news",
        "message": "문재인 대통령, '네거티브 규제' 방식의 필요성 거듭 강조",
        "name": "文대통령, 2주만에 또 '규제 혁신' 강조...\"행정이 너무 늦다\"",
        "type": "link"
    },
    {
        "count_commentss": 4,
        "count_reactions": 0,
        "count_shares": 0,
        "created_time": "2018-05-29 18:40:00",
        "id": "376570488117_10156472592588118",
        "link": "http://news.chosun.com/site/data/html_dir/2018/05/29/2018052902005.html?Dep0=facebook&news",
        "message": "북측은 아직 대표단 명단을 우리 측에 알려오지 않은 상태",
        "name": "정부, 北에 고위급 회담 대표단 명단 통보…국토부·체육부 차관 포함",
        "type": "link"
    },
    {
        "count_commentss": 89,
        "count_reactions": 0,
        "count_shares": 26,
        "created_time": "2018-05-29 18:20:00",
        "id": "376570488117_10156472582098118",
        "link": "http://news.chosun.com/site/data/html_dir/2018/05/29/2018052901690.html?Dep0=facebook&news",
        "message": "\"노동시간 단축은 우리 사회에 커다란 변화를 가져올 것\"",
        "name": "文대통령 \"노동시간 단축, 충분히 감당가능\"",
        "type": "link"
    },
    {
        "count_commentss": 1,
        "count_reactions": 0,
        "count_shares": 1,
        "created_time": "2018-05-29 18:00:00",
        "id": "376570488117_10156472551913118",
        "link": "http://news.chosun.com/site/data/html_dir/2018/05/29/2018052902107.html?Dep0=facebook&news",
        "message": "제자 24명의 어깨와 손, 허리 등을 만져 추행한 혐의로 기소",
        "name": "\"사랑한다고 하면 점수 올려준다\" 성추행 체육교사 징역형",
        "type": "link"
    },
    {
        "count_commentss": 42,
        "count_reactions": 0,
        "count_shares": 13,
        "created_time": "2018-05-29 17:40:00",
        "id": "376570488117_10156472548258118",
        "link": "http://news.chosun.com/site/data/html_dir/2018/05/29/2018052902134.html?Dep0=facebook&news",
        "message": "순식간에 2만5000여 개의 댓글 달려…\n\"당신 아버지 정책 때문에 이민자들은 아이 빼앗기는데\"",
        "name": "이방카, 아들 껴안는 사진 올리자 '비난'…\"이민자들은 아이 빼앗기는데\"",
        "type": "link"
    },
    {
        "count_commentss": 13,
        "count_reactions": 0,
        "count_shares": 0,
        "created_time": "2018-05-29 17:38:59",
        "id": "376570488117_10156472605958118",
        "link": "http://news.chosun.com/site/data/html_dir/2018/05/29/2018052902521.html",
        "message": "[속보] 대전 한화 공장서 폭발 추정 화재... 2명 사망·5명 부상",
        "name": "대전 한화 공장서 폭발 추정 화재... 2명 사망·5명 부상",
        "type": "link"
    },
    {
        "count_commentss": 16,
        "count_reactions": 0,
        "count_shares": 39,
        "created_time": "2018-05-29 17:20:01",
        "id": "376570488117_10156472537163118",
        "link": "http://news.chosun.com/site/data/html_dir/2018/05/29/2018052902081.html?Dep0=facebook&news",
        "message": "北이 경기 일으키는 '리비아식 해법'… 뭐가 문제일까?",
        "name": "카다피는 왜 죽었나, ‘리비아 모델’은 왜 문제인가",
        "type": "link"
    },
    {
        "count_commentss": 2,
        "count_reactions": 0,
        "count_shares": 5,
        "created_time": "2018-05-29 17:20:00",
        "id": "376570488117_10156472461193118",
        "link": "http://news.chosun.com/site/data/html_dir/2018/05/29/2018052901902.html?Dep0=facebook&news",
        "message": "길병원, '쪼개기 후원금' 형태로 국회의원들에게 불법 후원",
        "name": "복지부 간부, 길병원서 법인카드 8장으로 3억 5000만원 뇌물",
        "type": "link"
    },
    {
        "count_commentss": 31,
        "count_reactions": 0,
        "count_shares": 4,
        "created_time": "2018-05-29 17:00:01",
        "id": "376570488117_10156472455158118",
        "link": "http://news.chosun.com/site/data/html_dir/2018/05/29/2018052901741.html?Dep0=facebook&news",
        "message": "자신이 범야권의 대표주자라는 자신감 내비쳐",
        "name": "안철수 \"다른 후보가 깨끗이 양보하면 단일화 가능\"",
        "type": "link"
    },
    {
        "count_commentss": 1,
        "count_reactions": 0,
        "count_shares": 2,
        "created_time": "2018-05-29 16:40:00",
        "id": "376570488117_10156472425608118",
        "link": "http://news.chosun.com/site/data/html_dir/2018/05/29/2018052901784.html?Dep0=facebook&news",
        "message": "제품마다 내열 온도가 다를 수 있어 표시된 주의사항을 확인하고 사용해야 한다",
        "name": "식약처 \"멜라민수지 주방용품 직접 가열시 파손 우려\"",
        "type": "link"
    },
    {
        "count_commentss": 5,
        "count_reactions": 0,
        "count_shares": 1,
        "created_time": "2018-05-29 16:20:00",
        "id": "376570488117_10156472348838118",
        "link": "http://news.chosun.com/site/data/html_dir/2018/05/29/2018052901063.html?Dep0=facebook&news",
        "message": "\"어떤 하나의 대책을 가지고 일하는 것은 아니다\"",
        "name": "金 대법원장 “모든 것 열려있다”... 양승태 추가조사? 형사고발?",
        "type": "link"
    },
    {
        "count_commentss": 15,
        "count_reactions": 0,
        "count_shares": 26,
        "created_time": "2018-05-29 16:00:01",
        "id": "376570488117_10156472490718118",
        "link": "http://news.chosun.com/site/data/html_dir/2018/05/29/2018052901927.html?Dep0=facebook&news",
        "message": "\"최저임금 정책 너무 급해… 정부개입 줄여야\"",
        "name": "[J노믹스 3040 전문가에게 묻는다]① 이수형 서강대 교수 \"수단이 목표가 됐다...증거 기반 정책 펼쳐야\"",
        "type": "link"
    },
    {
        "count_commentss": 14,
        "count_reactions": 0,
        "count_shares": 4,
        "created_time": "2018-05-29 15:40:00",
        "id": "376570488117_10156472378373118",
        "link": "http://news.chosun.com/site/data/html_dir/2018/05/29/2018052901516.html?Dep0=facebook&news",
        "message": "與, 서울 구청장 싹쓸이 노리지만… 강남선 한국당 우세",
        "name": "[서울 서초구청장 여론조사] 조은희 44.2% 이정근 36%",
        "type": "link"
    },
    {
        "count_commentss": 1,
        "count_reactions": 0,
        "count_shares": 2,
        "created_time": "2018-05-29 15:20:00",
        "id": "376570488117_10156472338118118",
        "link": "http://news.chosun.com/site/data/html_dir/2018/05/29/2018052901357.html?Dep0=facebook&news",
        "message": "\"어떤 방법으로, 얼마나 널리 유포됐는지가 처벌 수위를 결정하는 중요한 기준\"",
        "name": "홍대 몰카와 사진관 몰카... 구속과 불구속의 차이는?",
        "type": "link"
    },
    {
        "count_commentss": 12,
        "count_reactions": 0,
        "count_shares": 10,
        "created_time": "2018-05-29 15:00:00",
        "id": "376570488117_10156472361578118",
        "link": "http://news.chosun.com/site/data/html_dir/2018/05/29/2018052900802.html?Dep0=facebook&news",
        "message": "\"문재인 대통령이 소득주도성장에서 벗어나지 못하고 계속 고집을 부리고 있다\"",
        "name": "유승민 \"文 정부 소득주도성장에 레드카드 꺼내야\"",
        "type": "link"
    },
    {
        "count_commentss": 20,
        "count_reactions": 0,
        "count_shares": 0,
        "created_time": "2018-05-29 14:40:00",
        "id": "376570488117_10156472370248118",
        "link": "http://news.chosun.com/site/data/html_dir/2018/05/29/2018052901537.html?Dep0=facebook&news",
        "message": "두 사람은 대마초 흡연 사실을 인정한 것으로 알려졌다",
        "name": "래퍼 씨잼·바스코, 대마초 흡연…\"녹음 끝내고 들어간다\" 글 남겨",
        "type": "link"
    },
    {
        "count_commentss": 29,
        "count_reactions": 0,
        "count_shares": 4,
        "created_time": "2018-05-29 14:20:00",
        "id": "376570488117_10156472376293118",
        "link": "http://news.chosun.com/site/data/html_dir/2018/05/29/2018052901550.html?Dep0=facebook&news",
        "message": "문 대통령, 모두발언에서 드루킹 특검법 관련 언급 안해",
        "name": "文대통령, '드루킹 특검법' 국무회의 의결",
        "type": "link"
    },
    {
        "count_commentss": 11,
        "count_reactions": 0,
        "count_shares": 2,
        "created_time": "2018-05-29 14:00:01",
        "id": "376570488117_10156472335458118",
        "link": "http://biz.chosun.com/site/data/html_dir/2018/05/29/2018052900994.html?Dep0=facebook&news",
        "message": "한·중 관계가 급격하게 얼어붙은지 1년여 만",
        "name": "'유커의 귀환'...4월 중국 노선 여객수 43.9% 증가",
        "type": "link"
    }
]